[
  {
    "inputs": [],
    "stateMutability": "nonpayable",
    "type": "constructor"
  },
  {
    "anonymous": false,
    "inputs": [
      {
        "indexed": false,
        "internalType": "address",
        "name": "merchant",
        "type": "address"
      },
      {
        "indexed": false,
        "internalType": "bool",
        "name": "isClosed",
        "type": "bool"
      }
    ],
    "name": "CloseMerchantAccount",
    "type": "event"
  },
  {
    "anonymous": false,
    "inputs": [
      {
        "indexed": false,
        "internalType": "address",
        "name": "merchant",
        "type": "address"
      },
      {
        "indexed": false,
        "internalType": "address",
        "name": "token",
        "type": "address"
      },
      {
        "indexed": false,
        "internalType": "uint256",
        "name": "amount",
        "type": "uint256"
      },
      {
        "indexed": false,
        "internalType": "uint256",
        "name": "transactionFeeAmount",
        "type": "uint256"
      }
    ],
    "name": "Flush",
    "type": "event"
  },
  {
    "anonymous": false,
    "inputs": [
      {
        "indexed": false,
        "internalType": "address",
        "name": "operator",
        "type": "address"
      },
      {
        "indexed": false,
        "internalType": "address",
        "name": "merchant",
        "type": "address"
      }
    ],
    "name": "Init",
    "type": "event"
  },
  {
    "anonymous": false,
    "inputs": [
      {
        "indexed": false,
        "internalType": "address",
        "name": "sender",
        "type": "address"
      },
      {
        "indexed": false,
        "internalType": "string",
        "name": "chargeCode",
        "type": "string"
      },
      {
        "indexed": false,
        "internalType": "address",
        "name": "token",
        "type": "address"
      },
      {
        "indexed": false,
        "internalType": "uint256",
        "name": "netValue",
        "type": "uint256"
      },
      {
        "indexed": false,
        "internalType": "uint256",
        "name": "feeValue",
        "type": "uint256"
      }
    ],
    "name": "Paid",
    "type": "event"
  },
  {
    "anonymous": false,
    "inputs": [
      {
        "indexed": false,
        "internalType": "string",
        "name": "chargeCode",
        "type": "string"
      },
      {
        "indexed": false,
        "internalType": "string",
        "name": "action",
        "type": "string"
      },
      {
        "indexed": false,
        "internalType": "bool",
        "name": "isToMerchant",
        "type": "bool"
      },
      {
        "indexed": false,
        "internalType": "address",
        "name": "walletReceiver",
        "type": "address"
      },
      {
        "indexed": false,
        "internalType": "address",
        "name": "token",
        "type": "address"
      },
      {
        "indexed": false,
        "internalType": "uint256",
        "name": "amount",
        "type": "uint256"
      },
      {
        "indexed": false,
        "internalType": "uint256",
        "name": "transactionFeeAmount",
        "type": "uint256"
      }
    ],
    "name": "ResolveUnlinkedPayment",
    "type": "event"
  },
  {
    "anonymous": false,
    "inputs": [
      {
        "indexed": false,
        "internalType": "address",
        "name": "admin",
        "type": "address"
      },
      {
        "indexed": false,
        "internalType": "address",
        "name": "token",
        "type": "address"
      },
      {
        "indexed": false,
        "internalType": "uint256",
        "name": "withdrawAmount",
        "type": "uint256"
      }
    ],
    "name": "WithdrawServiceFee",
    "type": "event"
  },
  {
    "inputs": [
      {
        "internalType": "address",
        "name": "",
        "type": "address"
      }
    ],
    "name": "balances",
    "outputs": [
      {
        "internalType": "uint256",
        "name": "netValue",
        "type": "uint256"
      },
      {
        "internalType": "uint256",
        "name": "fizenValue",
        "type": "uint256"
      }
    ],
    "stateMutability": "view",
    "type": "function",
    "constant": true
  },
  {
    "inputs": [],
    "name": "isClosed",
    "outputs": [
      {
        "internalType": "bool",
        "name": "",
        "type": "bool"
      }
    ],
    "stateMutability": "view",
    "type": "function",
    "constant": true
  },
  {
    "inputs": [],
    "name": "isInited",
    "outputs": [
      {
        "internalType": "bool",
        "name": "",
        "type": "bool"
      }
    ],
    "stateMutability": "view",
    "type": "function",
    "constant": true
  },
  {
    "inputs": [],
    "name": "operator",
    "outputs": [
      {
        "internalType": "address",
        "name": "",
        "type": "address"
      }
    ],
    "stateMutability": "view",
    "type": "function",
    "constant": true
  },
  {
    "inputs": [],
    "name": "serviceFee",
    "outputs": [
      {
        "internalType": "uint256",
        "name": "",
        "type": "uint256"
      }
    ],
    "stateMutability": "view",
    "type": "function",
    "constant": true
  },
  {
    "inputs": [],
    "name": "serviceFeeDecimal",
    "outputs": [
      {
        "internalType": "uint256",
        "name": "",
        "type": "uint256"
      }
    ],
    "stateMutability": "view",
    "type": "function",
    "constant": true
  },
  {
    "inputs": [],
    "name": "walletReceiver",
    "outputs": [
      {
        "internalType": "address",
        "name": "",
        "type": "address"
      }
    ],
    "stateMutability": "view",
    "type": "function",
    "constant": true
  },
  {
    "inputs": [
      {
        "internalType": "address",
        "name": "_operator",
        "type": "address"
      },
      {
        "internalType": "address",
        "name": "_walletReceiver",
        "type": "address"
      },
      {
        "internalType": "uint256",
        "name": "_serviceFee",
        "type": "uint256"
      },
      {
        "internalType": "uint256",
        "name": "_serviceFeeDecimal",
        "type": "uint256"
      }
    ],
    "name": "init",
    "outputs": [],
    "stateMutability": "nonpayable",
    "type": "function"
  },
  {
    "inputs": [
      {
        "internalType": "address",
        "name": "token",
        "type": "address"
      },
      {
        "internalType": "uint256",
        "name": "amount",
        "type": "uint256"
      },
      {
        "internalType": "uint256",
        "name": "transactionFeeAmount",
        "type": "uint256"
      }
    ],
    "name": "flush",
    "outputs": [],
    "stateMutability": "nonpayable",
    "type": "function"
  },
  {
    "inputs": [
      {
        "internalType": "uint256",
        "name": "_serviceFee",
        "type": "uint256"
      }
    ],
    "name": "setupServiceFee",
    "outputs": [],
    "stateMutability": "nonpayable",
    "type": "function"
  },
  {
    "inputs": [
      {
        "internalType": "bool",
        "name": "_isClosed",
        "type": "bool"
      }
    ],
    "name": "updateMerchantClose",
    "outputs": [],
    "stateMutability": "nonpayable",
    "type": "function"
  },
  {
    "inputs": [
      {
        "internalType": "address",
        "name": "admin",
        "type": "address"
      },
      {
        "internalType": "address",
        "name": "token",
        "type": "address"
      }
    ],
    "name": "withdrawServiceFee",
    "outputs": [],
    "stateMutability": "nonpayable",
    "type": "function"
  },
  {
    "inputs": [
      {
        "internalType": "string",
        "name": "chargeCode",
        "type": "string"
      },
      {
        "internalType": "string",
        "name": "action",
        "type": "string"
      },
      {
        "internalType": "bool",
        "name": "isToMerchant",
        "type": "bool"
      },
      {
        "internalType": "address",
        "name": "token",
        "type": "address"
      },
      {
        "internalType": "uint256",
        "name": "amount",
        "type": "uint256"
      },
      {
        "internalType": "uint256",
        "name": "transactionFeeAmount",
        "type": "uint256"
      }
    ],
    "name": "resolveUnlinkedPayment",
    "outputs": [],
    "stateMutability": "nonpayable",
    "type": "function"
  },
  {
    "inputs": [
      {
        "internalType": "string",
        "name": "chargeCode",
        "type": "string"
      },
      {
        "internalType": "address",
        "name": "token",
        "type": "address"
      },
      {
        "internalType": "uint256",
        "name": "amount",
        "type": "uint256"
      }
    ],
    "name": "transferToken",
    "outputs": [],
    "stateMutability": "nonpayable",
    "type": "function"
  },
  {
    "inputs": [
      {
        "internalType": "string",
        "name": "chargeCode",
        "type": "string"
      }
    ],
    "name": "transferCurrency",
    "outputs": [],
    "stateMutability": "payable",
    "type": "function",
    "payable": true
  }
]
